setup.py
gaussion_and_binomial_distributions/Binomialdistribution.py
gaussion_and_binomial_distributions/Gaussiandistribution.py
gaussion_and_binomial_distributions/Generaldistribution.py
gaussion_and_binomial_distributions/__init__.py
gaussion_and_binomial_distributions.egg-info/PKG-INFO
gaussion_and_binomial_distributions.egg-info/SOURCES.txt
gaussion_and_binomial_distributions.egg-info/dependency_links.txt
gaussion_and_binomial_distributions.egg-info/not-zip-safe
gaussion_and_binomial_distributions.egg-info/top_level.txt